biomaj_ftp/__init__.py
biomaj_ftp-3.0.7.data/scripts/biomaj_ftp_service.py
biomaj_ftp-3.0.7.dist-info/LICENSE
biomaj_ftp-3.0.7.dist-info/METADATA
biomaj_ftp-3.0.7.dist-info/WHEEL
biomaj_ftp-3.0.7.dist-info/top_level.txt
biomaj_ftp-3.0.7.dist-info/RECORD
