Metadata-Version: 2.1
Name: biomaj-ftp
Version: 3.0.7
Summary: BioMAJ FTP server
Home-page: http://biomaj.genouest.org
Author: Olivier Sallou
Author-email: olivier.sallou@irisa.fr
License: UNKNOWN
Download-URL: http://biomaj.genouest.org
Platform: UNKNOWN
Classifier: Development Status :: 5 - Production/Stable
Classifier: Environment :: Console
Classifier: Natural Language :: English
Classifier: Operating System :: POSIX :: Linux
Classifier: Intended Audience :: Science/Research
Classifier: Topic :: Scientific/Engineering :: Bio-Informatics
Classifier: License :: OSI Approved :: GNU Affero General Public License v3 or later (AGPLv3+)
Classifier: Programming Language :: Python :: 3
License-File: LICENSE
Requires-Dist: requests
Requires-Dist: pymongo (<4,>=3.12.3)
Requires-Dist: python-consul
Requires-Dist: pyftpdlib
Requires-Dist: biomaj-core
Requires-Dist: biomaj-user
Requires-Dist: PyYAML
